<?xml version="1.0" ?><list><Model.DaftarToko><namaToko>Mangut Lele Mbah Marto</namaToko><alamat>Jl. Sewon Indah, Panggungharjo, Sewon, Bantul</alamat><email>mbahmartoasik@gmail.com</email><noTelfon>08594378908</noTelfon><imgSrc>file:/C:/Users/Asus%20ROG/Downloads/mangut%20lele.png</imgSrc><ori>false</ori></Model.DaftarToko><Model.DaftarToko><namaToko>Mangut Lele Mbah Marto</namaToko><alamat>Jl. Sewon Indah, Panggungharjo, Sewon, Bantul</alamat><email>mbahmartoasik@gmail.com</email><noTelfon>08594378908</noTelfon><imgSrc>file:/C:/Users/Asus%20ROG/Downloads/mangut%20lele.png</imgSrc><ori>false</ori></Model.DaftarToko><Model.DaftarToko><namaToko>Gudeg Yu Djum</namaToko><alamat>Jalan Wijilan</alamat><email>yudjum65@gmail.com</email><noTelfon>646 1897</noTelfon><imgSrc>file:/D:/JAVA/Renjana/src/gambar/gudeg1%201.png</imgSrc><ori>false</ori></Model.DaftarToko><Model.DaftarToko><namaToko>wiefhweif</namaToko><alamat>wefwefwe</alamat><email>wefwqefqqwefw</email><noTelfon>wefqwfqw</noTelfon><imgSrc>file:/C:/Users/Acer/Downloads/938044.jpg</imgSrc><ori>false</ori></Model.DaftarToko></list>